openbench/__init__.py
openbench/_registry.py
openbench/config.py
openbench/eval_config.py
openbench/provider_config.py
openbench/py.typed
openbench/_cli/__init__.py
openbench/_cli/cache_command.py
openbench/_cli/describe_command.py
openbench/_cli/eval_command.py
openbench/_cli/eval_retry_command.py
openbench/_cli/export.py
openbench/_cli/export_command.py
openbench/_cli/list_command.py
openbench/_cli/utils.py
openbench/_cli/view_command.py
openbench/agents/__init__.py
openbench/agents/aider.py
openbench/agents/base.py
openbench/agents/claude.py
openbench/agents/docker_manager.py
openbench/agents/manager.py
openbench/agents/opencode.py
openbench/agents/roo.py
openbench/datasets/__init__.py
openbench/datasets/arc_agi.py
openbench/datasets/boolq.py
openbench/datasets/browsecomp.py
openbench/datasets/chartqapro.py
openbench/datasets/clockbench.py
openbench/datasets/cosafe_m2s.py
openbench/datasets/deep_research_bench.py
openbench/datasets/detailbench.py
openbench/datasets/drop.py
openbench/datasets/exercism.py
openbench/datasets/factscore.py
openbench/datasets/graphwalks.py
openbench/datasets/healthbench.py
openbench/datasets/hle.py
openbench/datasets/humaneval.py
openbench/datasets/ifbench.py
openbench/datasets/ifeval.py
openbench/datasets/livemcpbench.py
openbench/datasets/math.py
openbench/datasets/mathvista.py
openbench/datasets/mbpp.py
openbench/datasets/mgsm.py
openbench/datasets/mhj_m2s.py
openbench/datasets/mmmu.py
openbench/datasets/mmstar.py
openbench/datasets/mmvetv2.py
openbench/datasets/mockaime.py
openbench/datasets/mrcr.py
openbench/datasets/multichallenge.py
openbench/datasets/ocrbenchv2.py
openbench/datasets/political_evenhandedness.py
openbench/datasets/polyglotoxicity.py
openbench/datasets/rocketscience.py
openbench/datasets/rootly_terraform.py
openbench/datasets/safemt_m2s.py
openbench/datasets/scicode.py
openbench/datasets/sealqa.py
openbench/datasets/simpleqa.py
openbench/datasets/simpleqa_verified.py
openbench/datasets/smt.py
openbench-0.5.3.dist-info/licenses/LICENSE.md
openbench-0.5.3.dist-info/METADATA
openbench-0.5.3.dist-info/WHEEL
openbench-0.5.3.dist-info/entry_points.txt
openbench-0.5.3.dist-info/top_level.txt
openbench-0.5.3.dist-info/RECORD
