Metadata-Version: 2.4
Name: openbench
Version: 0.5.3
Summary: openbench - open source, replicable, and standardized evaluation infrastructure
Author: Aarush Sah, Groq
License: MIT
Project-URL: Homepage, https://github.com/groq/openbench
Project-URL: Repository, https://github.com/groq/openbench
Requires-Python: >=3.10
License-File: LICENSE.md
Requires-Dist: datasets>=3.6.0
Requires-Dist: groq>=0.33.0
Requires-Dist: inspect-ai==0.3.125
Requires-Dist: openai>=2.0.0
Requires-Dist: pillow>=10.0.0
Requires-Dist: jsonschema>=4.23.0
Requires-Dist: mcp>=1.13.1
Requires-Dist: platformdirs>=4.0.0
Requires-Dist: pydantic-settings>=2.9.1
Requires-Dist: scipy>=1.15.3
Requires-Dist: tiktoken>=0.11.0
Requires-Dist: typer>=0.15.3
Requires-Dist: numpy==2.2.6
Dynamic: license-file
